hurriyet/__init__.py
hurriyet/api.py
hurriyet/article.py
hurriyet/base.py
hurriyet/client.py
hurriyet/column.py
hurriyet/errors.py
hurriyet/models.py
hurriyet/news_photo_gallery.py
hurriyet/news_video.py
hurriyet/page.py
hurriyet/path.py
hurriyet/search.py
hurriyet/writer.py
python_hurriyet-1.0.0b1.dist-info/METADATA
python_hurriyet-1.0.0b1.dist-info/RECORD
python_hurriyet-1.0.0b1.dist-info/WHEEL
python_hurriyet-1.0.0b1.dist-info/top_level.txt
python_hurriyet-1.0.0b1.dist-info/zip-safe
