Metadata-Version: 2.1
Name: python-hurriyet
Version: 1.0.0b1
Summary: A Python client for the Hurriyet API.
Home-page: http://github.com/yakupadakli/python-hurriyet.git
Author: Yakup Adaklı
Author-email: yakup.adakli@gmail.com
License: MIT
Keywords: hurriyet library
Platform: UNKNOWN
Classifier: Development Status :: 3 - Alpha
Classifier: Topic :: Software Development :: Libraries
Classifier: License :: OSI Approved :: MIT License
Classifier: Operating System :: OS Independent
Classifier: Programming Language :: Python :: 2.7
Classifier: Programming Language :: Python :: 3.4
Classifier: Programming Language :: Python :: 3.5
Classifier: Programming Language :: Python :: 3.6
Requires-Dist: requests (==2.18.4)
Requires-Dist: six (==1.11.0)
